LICENSE
MANIFEST.in
README
automated-ebs-snapshots
setup.py
automated_ebs_snapshots/__init__.py
automated_ebs_snapshots/command_line_options.py
automated_ebs_snapshots/config_file_parser.py
automated_ebs_snapshots/connection_manager.py
automated_ebs_snapshots/daemon.py
automated_ebs_snapshots/settings.conf
automated_ebs_snapshots/snapshot_manager.py
automated_ebs_snapshots/valid_intervals.py
automated_ebs_snapshots/volume_manager.py
automated_ebs_snapshots.egg-info/PKG-INFO
automated_ebs_snapshots.egg-info/SOURCES.txt
automated_ebs_snapshots.egg-info/dependency_links.txt
automated_ebs_snapshots.egg-info/not-zip-safe
automated_ebs_snapshots.egg-info/requires.txt
automated_ebs_snapshots.egg-info/top_level.txt