Metadata-Version: 1.1
Name: automated-ebs-snapshots
Version: 0.5.0
Summary: Automatic backup management of AWS EC2 EBS volumes
Home-page: https://github.com/skymill/automated-ebs-snapshots
Author: Sebastian Dahlgren, Skymill Solutions
Author-email: sebastian.dahlgren@skymill.se
License: Apache License, Version 2.0
Keywords: aws amazon web services ec2 ebs snapshot
Platform: Any
Classifier: Development Status :: 4 - Beta
Classifier: Environment :: Console
Classifier: License :: OSI Approved :: Apache Software License
Classifier: Operating System :: OS Independent
Classifier: Programming Language :: Python
